llm_to_toon/__init__.py
llm_to_toon-0.0.42.dist-info/METADATA
llm_to_toon-0.0.42.dist-info/WHEEL
llm_to_toon-0.0.42.dist-info/top_level.txt
llm_to_toon-0.0.42.dist-info/RECORD
