Metadata-Version: 2.4
Name: llm-to-toon
Version: 0.0.42
Summary: Tiny wrapper exposing Prompture helpers to convert LLM output into TOON.
Author-email: Juan Denis <juan@vene.co>
License: MIT
Keywords: llm,toon,prompt,structured-output
Requires-Python: >=3.10
Requires-Dist: prompture>=0.0.42
